README
setup.py
ltprotocol/__init__.py
ltprotocol/ltprotocol.py
ltprotocol.egg-info/PKG-INFO
ltprotocol.egg-info/SOURCES.txt
ltprotocol.egg-info/dependency_links.txt
ltprotocol.egg-info/requires.txt
ltprotocol.egg-info/top_level.txt
