Metadata-Version: 1.0
Name: ltprotocol
Version: 0.1.8
Summary: Twisted-based client and server for protocols which begin with a length and type field
Home-page: http://www.dound.com/projects/python/ltprotocol/
Author: David Underhill
Author-email: dgu@cs.stanford.edu
License: GPL
Keywords: networking twisted protocol nonblocking internet length type
Platform: UNKNOWN
Classifier: License :: OSI Approved :: GNU General Public License (GPL)
Classifier: Programming Language :: Python
Classifier: Development Status :: 4 - Beta
Classifier: Intended Audience :: Developers
Classifier: Topic :: Internet
